{
  "options": [
    {
      "key": "DAIRY_FREE",
      "text": "Dairy Free",
      "value": "DAIRY_FREE"
    },
    {
      "key": "VEGETARIAN",
      "text": "Vegetarian",
      "value": "VEGETARIAN"
    },
    {
      "key": "VEGAN",
      "text": "Vegan",
      "value": "VEGAN"
    },
    {
      "key": "PEANUT_FREE",
      "text": "Peanut Free",
      "value": "PEANUT_FREE"
    },
    {
      "key": "GLUTEN_FREE",
      "text": "Gluten Free",
      "value": "GLUTEN_FREE"
    },
    {
      "key": "KOSHER",
      "text": "Kosher",
      "value": "KOSHER"
    },
    {
      "key": "HALAL",
      "text": "Halal",
      "value": "HALAL"
    }
  ]
}
